impossible_fx
