Metadata-Version: 1.1
Name: fx-python-sdk
Version: 0.1.1
Summary: Python SDK for Impossible FX
Home-page: https://www.impossiblesoftware.com/
Author: Impossible Software
Author-email: gh@impossiblesoftware.com
License: MIT License
Platform: UNKNOWN
Classifier: Development Status :: 3 - Alpha
Classifier: Intended Audience :: Developers
Classifier: License :: OSI Approved :: MIT License
Classifier: Programming Language :: Python
Classifier: Topic :: Multimedia :: Video
